<eventScriptManager>
   <events>
      <scriptedEvent>
         <executiontime>0</executiontime>
         <event class="presage.events.CoreEvents$ActivateParticipant">
            <participantname>seed0</participantname>
         </event>
         <uuidstring>2d0154ed-ad12-44bd-bc81-91013d4bb70d</uuidstring>
      </scriptedEvent>
      <scriptedEvent>
         <executiontime>0</executiontime>
         <event class="presage.events.CoreEvents$ActivateParticipant">
            <participantname>seed1</participantname>
         </event>
         <uuidstring>1b8fdaf3-111c-43ef-8959-715968228a1f</uuidstring>
      </scriptedEvent>
      <scriptedEvent>
         <executiontime>0</executiontime>
         <event class="presage.events.CoreEvents$ActivateParticipant">
            <participantname>cell0</participantname>
         </event>
         <uuidstring>469bd7cd-22b7-4f72-96d6-afd59f5b0100</uuidstring>
      </scriptedEvent>
      <scriptedEvent>
         <executiontime>0</executiontime>
         <event class="presage.events.CoreEvents$ActivateParticipant">
            <participantname>cell1</participantname>
         </event>
         <uuidstring>8156abf8-d414-43e7-b322-97976f44282d</uuidstring>
      </scriptedEvent>
      <scriptedEvent>
         <executiontime>0</executiontime>
         <event class="presage.events.CoreEvents$ActivateParticipant">
            <participantname>cell2</participantname>
         </event>
         <uuidstring>ae3d6506-e98d-46c2-b320-c143296ba467</uuidstring>
      </scriptedEvent>
      <scriptedEvent>
         <executiontime>0</executiontime>
         <event class="presage.events.CoreEvents$ActivateParticipant">
            <participantname>cell3</participantname>
         </event>
         <uuidstring>82872f6f-888e-4bff-a61e-c9632bd04356</uuidstring>
      </scriptedEvent>
      <scriptedEvent>
         <executiontime>0</executiontime>
         <event class="presage.events.CoreEvents$ActivateParticipant">
            <participantname>cell4</participantname>
         </event>
         <uuidstring>f94b3ca9-6126-4056-9c70-01ac5fac754c</uuidstring>
      </scriptedEvent>
      <scriptedEvent>
         <executiontime>0</executiontime>
         <event class="presage.events.CoreEvents$ActivateParticipant">
            <participantname>cell5</participantname>
         </event>
         <uuidstring>4d54f9ff-1040-491a-a015-15606d2e6d79</uuidstring>
      </scriptedEvent>
      <scriptedEvent>
         <executiontime>0</executiontime>
         <event class="presage.events.CoreEvents$ActivateParticipant">
            <participantname>cell6</participantname>
         </event>
         <uuidstring>79144d80-f4cc-468c-bb09-62d03a4dd947</uuidstring>
      </scriptedEvent>
      <scriptedEvent>
         <executiontime>0</executiontime>
         <event class="presage.events.CoreEvents$ActivateParticipant">
            <participantname>cell7</participantname>
         </event>
         <uuidstring>50ba9968-aa8a-4211-9585-ada0fb70f3b2</uuidstring>
      </scriptedEvent>
      <scriptedEvent>
         <executiontime>0</executiontime>
         <event class="presage.events.CoreEvents$ActivateParticipant">
            <participantname>cell8</participantname>
         </event>
         <uuidstring>7e31db8c-5f4e-4013-8d48-0339891d1997</uuidstring>
      </scriptedEvent>
      <scriptedEvent>
         <executiontime>0</executiontime>
         <event class="presage.events.CoreEvents$ActivateParticipant">
            <participantname>cell9</participantname>
         </event>
         <uuidstring>0020e967-2447-456e-b819-42a0bbbef65d</uuidstring>
      </scriptedEvent>
      <scriptedEvent>
         <executiontime>0</executiontime>
         <event class="presage.events.CoreEvents$ActivateParticipant">
            <participantname>cell10</participantname>
         </event>
         <uuidstring>b2f71e3b-738d-415f-9d3e-657e28877aef</uuidstring>
      </scriptedEvent>
      <scriptedEvent>
         <executiontime>0</executiontime>
         <event class="presage.events.CoreEvents$ActivateParticipant">
            <participantname>cell11</participantname>
         </event>
         <uuidstring>0f9f0f8b-b5bd-41ec-bf17-184529e6e7d1</uuidstring>
      </scriptedEvent>
      <scriptedEvent>
         <executiontime>0</executiontime>
         <event class="presage.events.CoreEvents$ActivateParticipant">
            <participantname>cell12</participantname>
         </event>
         <uuidstring>3b1e39ee-d12b-42ce-9793-0c135d1e05b2</uuidstring>
      </scriptedEvent>
      <scriptedEvent>
         <executiontime>0</executiontime>
         <event class="presage.events.CoreEvents$ActivateParticipant">
            <participantname>cell13</participantname>
         </event>
         <uuidstring>b1fcd289-ad28-4fe3-acc8-21421e074b48</uuidstring>
      </scriptedEvent>
      <scriptedEvent>
         <executiontime>0</executiontime>
         <event class="presage.events.CoreEvents$ActivateParticipant">
            <participantname>cell14</participantname>
         </event>
         <uuidstring>a39ca1c6-d68b-42e8-8109-526c0a840d27</uuidstring>
      </scriptedEvent>
      <scriptedEvent>
         <executiontime>0</executiontime>
         <event class="presage.events.CoreEvents$ActivateParticipant">
            <participantname>cell15</participantname>
         </event>
         <uuidstring>4fbc6b81-85ce-443d-b39f-faf454a39763</uuidstring>
      </scriptedEvent>
      <scriptedEvent>
         <executiontime>0</executiontime>
         <event class="presage.events.CoreEvents$ActivateParticipant">
            <participantname>cell16</participantname>
         </event>
         <uuidstring>4ddf1b1d-07ef-49eb-8a46-659574905509</uuidstring>
      </scriptedEvent>
      <scriptedEvent>
         <executiontime>0</executiontime>
         <event class="presage.events.CoreEvents$ActivateParticipant">
            <participantname>cell17</participantname>
         </event>
         <uuidstring>638c5b52-a4fb-49c4-81e1-b392155c6199</uuidstring>
      </scriptedEvent>
      <scriptedEvent>
         <executiontime>0</executiontime>
         <event class="presage.events.CoreEvents$ActivateParticipant">
            <participantname>cell18</participantname>
         </event>
         <uuidstring>ce172c81-b6f2-4b69-a9a4-e9c64894d550</uuidstring>
      </scriptedEvent>
      <scriptedEvent>
         <executiontime>0</executiontime>
         <event class="presage.events.CoreEvents$ActivateParticipant">
            <participantname>cell19</participantname>
         </event>
         <uuidstring>6c499fc5-ae74-4b46-a5e1-54c02ebec250</uuidstring>
      </scriptedEvent>
      <scriptedEvent>
         <executiontime>0</executiontime>
         <event class="presage.events.CoreEvents$ActivateParticipant">
            <participantname>cell20</participantname>
         </event>
         <uuidstring>574e9b92-85b9-4679-8075-f829e3d0b2e3</uuidstring>
      </scriptedEvent>
      <scriptedEvent>
         <executiontime>0</executiontime>
         <event class="presage.events.CoreEvents$ActivateParticipant">
            <participantname>cell21</participantname>
         </event>
         <uuidstring>9836b1c3-0e1e-4182-ab97-ea59bb4bf791</uuidstring>
      </scriptedEvent>
      <scriptedEvent>
         <executiontime>0</executiontime>
         <event class="presage.events.CoreEvents$ActivateParticipant">
            <participantname>cell22</participantname>
         </event>
         <uuidstring>3bd2480f-7970-4d3a-8a56-6387724e87f8</uuidstring>
      </scriptedEvent>
      <scriptedEvent>
         <executiontime>0</executiontime>
         <event class="presage.events.CoreEvents$ActivateParticipant">
            <participantname>cell23</participantname>
         </event>
         <uuidstring>934204b0-65b6-4cde-9944-6f870b0df1ce</uuidstring>
      </scriptedEvent>
      <scriptedEvent>
         <executiontime>0</executiontime>
         <event class="presage.events.CoreEvents$ActivateParticipant">
            <participantname>cell24</participantname>
         </event>
         <uuidstring>f2d147b7-c87d-408a-b1c9-ba74825b269f</uuidstring>
      </scriptedEvent>
      <scriptedEvent>
         <executiontime>0</executiontime>
         <event class="presage.events.CoreEvents$ActivateParticipant">
            <participantname>cell25</participantname>
         </event>
         <uuidstring>24721b27-210b-4603-b8fb-71090879d66d</uuidstring>
      </scriptedEvent>
      <scriptedEvent>
         <executiontime>0</executiontime>
         <event class="presage.events.CoreEvents$ActivateParticipant">
            <participantname>cell26</participantname>
         </event>
         <uuidstring>ba4207a1-d489-4ba7-b2b8-4a2e132d9484</uuidstring>
      </scriptedEvent>
      <scriptedEvent>
         <executiontime>0</executiontime>
         <event class="presage.events.CoreEvents$ActivateParticipant">
            <participantname>cell27</participantname>
         </event>
         <uuidstring>37ad34bc-ad83-4481-87cb-7f4c1db9f131</uuidstring>
      </scriptedEvent>
      <scriptedEvent>
         <executiontime>0</executiontime>
         <event class="presage.events.CoreEvents$ActivateParticipant">
            <participantname>cell28</participantname>
         </event>
         <uuidstring>3b9a5817-019a-4a57-a778-3fb6bc256442</uuidstring>
      </scriptedEvent>
      <scriptedEvent>
         <executiontime>0</executiontime>
         <event class="presage.events.CoreEvents$ActivateParticipant">
            <participantname>cell29</participantname>
         </event>
         <uuidstring>41d59073-25ec-45b1-a76d-caefa06f46e7</uuidstring>
      </scriptedEvent>
      <scriptedEvent>
         <executiontime>0</executiontime>
         <event class="presage.events.CoreEvents$ActivateParticipant">
            <participantname>cell30</participantname>
         </event>
         <uuidstring>50d675ef-26fd-4172-81d6-52e4c156f5f3</uuidstring>
      </scriptedEvent>
      <scriptedEvent>
         <executiontime>0</executiontime>
         <event class="presage.events.CoreEvents$ActivateParticipant">
            <participantname>cell31</participantname>
         </event>
         <uuidstring>8028dbb4-d7a6-44f8-a38d-7d1512db7c02</uuidstring>
      </scriptedEvent>
      <scriptedEvent>
         <executiontime>0</executiontime>
         <event class="presage.events.CoreEvents$ActivateParticipant">
            <participantname>cell32</participantname>
         </event>
         <uuidstring>f3aee379-07d3-45fe-ae18-c7d9dd07aec0</uuidstring>
      </scriptedEvent>
      <scriptedEvent>
         <executiontime>0</executiontime>
         <event class="presage.events.CoreEvents$ActivateParticipant">
            <participantname>cell33</participantname>
         </event>
         <uuidstring>5a427f89-6adb-44e8-9b3b-12cfaef70fc7</uuidstring>
      </scriptedEvent>
      <scriptedEvent>
         <executiontime>0</executiontime>
         <event class="presage.events.CoreEvents$ActivateParticipant">
            <participantname>cell34</participantname>
         </event>
         <uuidstring>4e477bd5-0934-4687-a1b4-71c377522789</uuidstring>
      </scriptedEvent>
      <scriptedEvent>
         <executiontime>0</executiontime>
         <event class="presage.events.CoreEvents$ActivateParticipant">
            <participantname>cell35</participantname>
         </event>
         <uuidstring>cfbd7bdc-9fbb-471a-bdef-699eec8173df</uuidstring>
      </scriptedEvent>
      <scriptedEvent>
         <executiontime>0</executiontime>
         <event class="presage.events.CoreEvents$ActivateParticipant">
            <participantname>cell36</participantname>
         </event>
         <uuidstring>4352eeb0-4df8-474d-906a-98c9428d68fe</uuidstring>
      </scriptedEvent>
      <scriptedEvent>
         <executiontime>0</executiontime>
         <event class="presage.events.CoreEvents$ActivateParticipant">
            <participantname>cell37</participantname>
         </event>
         <uuidstring>870ef4c6-b889-4527-926a-c7dcaac8f530</uuidstring>
      </scriptedEvent>
      <scriptedEvent>
         <executiontime>0</executiontime>
         <event class="presage.events.CoreEvents$ActivateParticipant">
            <participantname>cell38</participantname>
         </event>
         <uuidstring>5d9480e1-2199-46e0-b9aa-78d7c442a0f4</uuidstring>
      </scriptedEvent>
      <scriptedEvent>
         <executiontime>0</executiontime>
         <event class="presage.events.CoreEvents$ActivateParticipant">
            <participantname>cell39</participantname>
         </event>
         <uuidstring>ea63eed0-db6a-481c-8fdf-bf5c1fad5c42</uuidstring>
      </scriptedEvent>
      <scriptedEvent>
         <executiontime>0</executiontime>
         <event class="presage.events.CoreEvents$ActivateParticipant">
            <participantname>cell40</participantname>
         </event>
         <uuidstring>a9aa32fa-79aa-4d4f-94fe-cdca9a23e6b2</uuidstring>
      </scriptedEvent>
      <scriptedEvent>
         <executiontime>0</executiontime>
         <event class="presage.events.CoreEvents$ActivateParticipant">
            <participantname>cell41</participantname>
         </event>
         <uuidstring>bdefa930-123e-40b1-8579-ca339efe9ecc</uuidstring>
      </scriptedEvent>
      <scriptedEvent>
         <executiontime>0</executiontime>
         <event class="presage.events.CoreEvents$ActivateParticipant">
            <participantname>cell42</participantname>
         </event>
         <uuidstring>48a19f4a-ca18-4d69-a795-21087e62ae6f</uuidstring>
      </scriptedEvent>
      <scriptedEvent>
         <executiontime>0</executiontime>
         <event class="presage.events.CoreEvents$ActivateParticipant">
            <participantname>cell43</participantname>
         </event>
         <uuidstring>33f72592-65cc-4f3d-bb65-e624a2b9d2f0</uuidstring>
      </scriptedEvent>
      <scriptedEvent>
         <executiontime>0</executiontime>
         <event class="presage.events.CoreEvents$ActivateParticipant">
            <participantname>cell44</participantname>
         </event>
         <uuidstring>42196f78-4e56-4703-b1ac-840d0286bfe1</uuidstring>
      </scriptedEvent>
      <scriptedEvent>
         <executiontime>0</executiontime>
         <event class="presage.events.CoreEvents$ActivateParticipant">
            <participantname>cell45</participantname>
         </event>
         <uuidstring>031b6f65-b822-4d5f-9b50-f7806be80eec</uuidstring>
      </scriptedEvent>
      <scriptedEvent>
         <executiontime>0</executiontime>
         <event class="presage.events.CoreEvents$ActivateParticipant">
            <participantname>cell46</participantname>
         </event>
         <uuidstring>fa92dc23-ec74-4b98-9c48-671a58dca38c</uuidstring>
      </scriptedEvent>
      <scriptedEvent>
         <executiontime>0</executiontime>
         <event class="presage.events.CoreEvents$ActivateParticipant">
            <participantname>cell47</participantname>
         </event>
         <uuidstring>07aff92f-75d3-442d-ac01-46c34bfe07a8</uuidstring>
      </scriptedEvent>
      <scriptedEvent>
         <executiontime>0</executiontime>
         <event class="presage.events.CoreEvents$ActivateParticipant">
            <participantname>cell48</participantname>
         </event>
         <uuidstring>343cfb8c-e810-4385-a0dd-b252f0e94157</uuidstring>
      </scriptedEvent>
      <scriptedEvent>
         <executiontime>0</executiontime>
         <event class="presage.events.CoreEvents$ActivateParticipant">
            <participantname>cell49</participantname>
         </event>
         <uuidstring>83ef6fc9-13f8-4715-9ac9-0afceafb3777</uuidstring>
      </scriptedEvent>
   </events>
   <preevents/>
   <postevents/>
</eventScriptManager>